{"cameraMode":{"drawMode":0,"name":"Shaded","section":"Shading Mode"},"sceneLighting":true,"audioPlay":false,"sceneViewState":{"m_AlwaysRefresh":false,"showFog":true,"showSkybox":true,"showFlares":true,"showImageEffects":true,"showParticleSystems":true,"showVisualEffectGraphs":true,"m_FxEnabled":true},"in2DMode":false,"pivot":{"x":2.2340078353881838,"y":-1.2364788055419922,"z":-5.377449035644531},"rotation":{"x":-0.1892680525779724,"y":0.16577279567718507,"z":-0.03253526613116264,"w":-0.9674323201179504},"size":10.827323913574219,"orthographic":false}